CHANGELOG.rst
MANIFEST.in
README.rst
setup.py
echarts_united_kingdom_pypkg/__init__.py
echarts_united_kingdom_pypkg/_version.py
echarts_united_kingdom_pypkg/constants.py
echarts_united_kingdom_pypkg.egg-info/PKG-INFO
echarts_united_kingdom_pypkg.egg-info/SOURCES.txt
echarts_united_kingdom_pypkg.egg-info/dependency_links.txt
echarts_united_kingdom_pypkg.egg-info/not-zip-safe
echarts_united_kingdom_pypkg.egg-info/requires.txt
echarts_united_kingdom_pypkg.egg-info/top_level.txt
echarts_united_kingdom_pypkg/resources/registry.json
echarts_united_kingdom_pypkg/resources/echarts-united-kingdom-js/main.js
echarts_united_kingdom_pypkg/resources/echarts-united-kingdom-js/westminster_2016_uk.js